ucarball/__init__.py
ucarball/command_line.py
ucarball/decompile_replays.py
ucarball/analysis/PROTOBUF_VERSION
ucarball/analysis/__init__.py
ucarball/analysis/analysis_manager.py
ucarball/analysis/cleaner/__init__.py
ucarball/analysis/cleaner/cleaner.py
ucarball/analysis/cleaner/frame_cleaner.py
ucarball/analysis/constants/__init__.py
ucarball/analysis/constants/basic_math.py
ucarball/analysis/constants/dropshot.py
ucarball/analysis/constants/field_constants.py
ucarball/analysis/constants/playlist.py
ucarball/analysis/events/__init__.py
ucarball/analysis/events/carry_detection.py
ucarball/analysis/events/event_creator.py
ucarball/analysis/events/boost_pad_detection/__init__.py
ucarball/analysis/events/boost_pad_detection/pickup_analysis.py
ucarball/analysis/events/bump_detection/__init__.py
ucarball/analysis/events/bump_detection/bump_analysis.py
ucarball/analysis/events/dropshot/__init__.py
ucarball/analysis/events/dropshot/ball.py
ucarball/analysis/events/dropshot/damage.py
ucarball/analysis/events/fifty_fifty/__init__.py
ucarball/analysis/events/fifty_fifty/fifty_analysis.py
ucarball/analysis/events/hit_detection/__init__.py
ucarball/analysis/events/hit_detection/base_hit.py
ucarball/analysis/events/hit_detection/hit_analysis.py
"ucarball/analysis/events/hit_detection/hitbox/Vehicle Specifications v1.39 - Hitboxes, Handling.xlsx"
ucarball/analysis/events/hit_detection/hitbox/__init__.py
ucarball/analysis/events/hit_detection/hitbox/car.py
ucarball/analysis/events/hit_detection/hitbox/hitbox.py
ucarball/analysis/events/hit_pressure/__init__.py
ucarball/analysis/events/hit_pressure/pressure_analysis.py
ucarball/analysis/events/kickoff_detection/__init__.py
ucarball/analysis/events/kickoff_detection/kickoff_analysis.py
ucarball/analysis/saltie_game/__init__.py
ucarball/analysis/saltie_game/saltie_game.py
ucarball/analysis/saltie_game/metadata/ApiDemo.py
ucarball/analysis/saltie_game/metadata/ApiGame.py
ucarball/analysis/saltie_game/metadata/ApiGoal.py
ucarball-2.0.0.dist-info/licenses/LICENSE
ucarball-2.0.0.dist-info/licenses/NOTICE
ucarball-2.0.0.dist-info/METADATA
ucarball-2.0.0.dist-info/WHEEL
ucarball-2.0.0.dist-info/entry_points.txt
ucarball-2.0.0.dist-info/top_level.txt
ucarball-2.0.0.dist-info/RECORD
