Metadata-Version: 2.4
Name: ucarball
Version: 2.0.0
Summary: Rocket League replay parsing and analysis.
Home-page: https://github.com/SaltieRL/ucarball
Author: AirwolfTomato, sciguymjm, and contributors
Author-email: vijay@ashokn.org
License: Apache 2.0
Keywords: rocket-league
License-File: LICENSE
License-File: NOTICE
Requires-Dist: pandas>=2.3.0
Requires-Dist: protobuf>=4.21.0
Requires-Dist: xlrd>=2.0.0
Requires-Dist: numpy>=1.23.0
Requires-Dist: uboxcars-py==0.1.*
Dynamic: author
Dynamic: author-email
Dynamic: description
Dynamic: description-content-type
Dynamic: home-page
Dynamic: keywords
Dynamic: license
Dynamic: license-file
Dynamic: requires-dist
Dynamic: summary
